Workbook

Sheet AB Test Analysis
A1: Milestone | A/B Testing for H&M | F1: group | G1: subject line | H1: opened
F2: control | G2: =IF(ABTest[[#This Row],[group]]="control","20% off + free shipping","Your last chance to score 20% off + free shipping") -> 20% off + free shipping | H2: 0
A3: • All of your answers should be typed or pasted into the grey boxes. • Questions with grey answer boxes expect a specific answer. Once you input the correct answer, the question number box will change from blue to green. • Questions with yellow answer boxes are free-response questions. There will be no change in the question number boxes (in blue), regardless of your answer. • Hover your cursor over the blue hint box to get a helpful hint! | F3: control | G3: =IF(ABTest[[#This Row],[group]]="control","20% off + free shipping","Your last chance to score 20% off + free shipping") -> 20% off + free shipping | H3: 0
F4: control | G4: =IF(ABTest[[#This Row],[group]]="control","20% off + free shipping","Your last chance to score 20% off + free shipping") -> 20% off + free shipping | H4: 0
F5: test | G5: =IF(ABTest[[#This Row],[group]]="control","20% off + free shipping","Your last chance to score 20% off + free shipping") -> Your last chance to score 20% off + free shipping | H5: 0
F6: test | G6: =IF(ABTest[[#This Row],[group]]="control","20% off + free shipping","Your last chance to score 20% off + free shipping") -> Your last chance to score 20% off + free shipping | H6: 0
F7: test | G7: =IF(ABTest[[#This Row],[group]]="control","20% off + free shipping","Your last chance to score 20% off + free shipping") -> Your last chance to score 20% off + free shipping | H7: 0
F8: control | G8: =IF(ABTest[[#This Row],[group]]="control","20% off + free shipping","Your last chance to score 20% off + free shipping") -> 20% off + free shipping | H8: 0
F9: control | G9: =IF(ABTest[[#This Row],[group]]="control","20% off + free shipping","Your last chance to score 20% off + free shipping") -> 20% off + free shipping | H9: 0
F10: test | G10: =IF(ABTest[[#This Row],[group]]="control","20% off + free shipping","Your last chance to score 20% off + free shipping") -> Your last chance to score 20% off + free shipping | H10: 1
F11: test | G11: =IF(ABTest[[#This Row],[group]]="control","20% off + free shipping","Your last chance to score 20% off + free shipping") -> Your last chance to score 20% off + free shipping | H11: 0
F12: test | G12: =IF(ABTest[[#This Row],[group]]="control","20% off + free shipping","Your last chance to score 20% off + free shipping") -> Your last chance to score 20% off + free shipping | H12: 0
F13: test | G13: =IF(ABTest[[#This Row],[group]]="control","20% off + free shipping","Your last chance to score 20% off + free shipping") -> Your last chance to score 20% off + free shipping | H13: 0
A14: Part 1: A/B Test Design & Identifying Potential Issues | F14: control | G14: =IF(ABTest[[#This Row],[group]]="control","20% off + free shipping","Your last chance to score 20% off + free shipping") -> 20% off + free shipping | H14: 0
F15: control | G15: =IF(ABTest[[#This Row],[group]]="control","20% off + free shipping","Your last chance to score 20% off + free shipping") -> 20% off + free shipping | H15: 1
A16: 1 | B16: In a sentence or two, state the null hypothesis for H&M's A/B test. | F16: test | G16: =IF(ABTest[[#This Row],[group]]="control","20% off + free shipping","Your last chance to score 20% off + free shipping") -> Your last chance to score 20% off + free shipping | H16: 0
A17: Changing the H&M's subject line from "The appearance of 20% off + free shipping" to "Your last chance to score 20% off + free shipping" will result in no change/Decrease in open rates for the email. | F17: control | G17: =IF(ABTest[[#This Row],[group]]="control","20% off + free shipping","Your last chance to score 20% off + free shipping") -> 20% off + free shipping | H17: 0
F18: control | G18: =IF(ABTest[[#This Row],[group]]="control","20% off + free shipping","Your last chance to score 20% off + free shipping") -> 20% off + free shipping | H18: 0
A19: 2 | B19: In a sentence or two, state the alternative hypothesis for H&M's A/B test. | F19: test | G19: =IF(ABTest[[#This Row],[group]]="control","20% off + free shipping","Your last chance to score 20% off + free shipping") -> Your last chance to score 20% off + free shipping | H19: 0
A20: Changing the H&M's subject line from "The appearance of 20% off + free shipping" to "Your last chance to score 20% off + free shipping" will result in an increase in open rates for the email. | F20: test | G20: =IF(ABTest[[#This Row],[group]]="control","20% off + free shipping","Your last chance to score 20% off + free shipping") -> Your last chance to score 20% off + free shipping | H20: 0
F21: control | G21: =IF(ABTest[[#This Row],[group]]="control","20% off + free shipping","Your last chance to score 20% off + free shipping") -> 20% off + free shipping | H21: 0
A22: Use the A/B Test Sample Size Calculator linked below to help you answer the following questions. | F22: test | G22: =IF(ABTest[[#This Row],[group]]="control","20% off + free shipping","Your last chance to score 20% off + free shipping") -> Your last chance to score 20% off + free shipping | H22: 0
A23: =HYPERLINK("https://www.statsig.com/calculator","A/B Test Sample Size Calculator") -> A/B Test Sample Size Calculator | F23: control | G23: =IF(ABTest[[#This Row],[group]]="control","20% off + free shipping","Your last chance to score 20% off + free shipping") -> 20% off + free shipping | H23: 0
A24: Historically, promotional emails have had an open rate of 18%. The company wants to see the new subject line increase that to an open rate of 20%. | F24: control | G24: =IF(ABTest[[#This Row],[group]]="control","20% off + free shipping","Your last chance to score 20% off + free shipping") -> 20% off + free shipping | H24: 0
F25: test | G25: =IF(ABTest[[#This Row],[group]]="control","20% off + free shipping","Your last chance to score 20% off + free shipping") -> Your last chance to score 20% off + free shipping | H25: 1
A26: 3 | B26: What is the minimum detectable effect associated with that increase in open rate? | C26: 0.11 | D26: Hint! | F26: control | G26: =IF(ABTest[[#This Row],[group]]="control","20% off + free shipping","Your last chance to score 20% off + free shipping") -> 20% off + free shipping | H26: 0
F27: control | G27: =IF(ABTest[[#This Row],[group]]="control","20% off + free shipping","Your last chance to score 20% off + free shipping") -> 20% off + free shipping | H27: 0
A28: 4 | B28: What total sample size is required to reliably detect that level of increase? | C28: 9300 | D28: Hint! | F28: test | G28: =IF(ABTest[[#This Row],[group]]="control","20% off + free shipping","Your last chance to score 20% off + free shipping") -> Your last chance to score 20% off + free shipping | H28: 0
F29: test | G29: =IF(ABTest[[#This Row],[group]]="control","20% off + free shipping","Your last chance to score 20% off + free shipping") -> Your last chance to score 20% off + free shipping | H29: 1
A30: Before launching any A/B test, it’s crucial to identify potential risks or confounding factors that could skew the results. As the analyst, you need to be prepared to be asked "How do we know if this test is valid?" | F30: test | G30: =IF(ABTest[[#This Row],[group]]="control","20% off + free shipping","Your last chance to score 20% off + free shipping") -> Your last chance to score 20% off + free shipping | H30: 0
F31: control | G31: =IF(ABTest[[#This Row],[group]]="control","20% off + free shipping","Your last chance to score 20% off + free shipping") -> 20% off + free shipping | H31: 0 | J31: =SUM(H2:H9437) -> 1730
A32: 5 | B32: Use ChatGPT to generate a list of confounding factors by asking "What factors could skew the results of an A/B test like this, and how might they influence our findings or effect the results?" You might also try "What are common mistakes to avoid when designing an A/B test?" After reviewing ChatGPT’s response, identify at least two confounding factors that could impact the experiment. Write a develop a brief strategy (one-to-two sentences) for how you would mitigate these issues if you were a part of designing a similar A/B test. | F32: control | G32: =IF(ABTest[[#This Row],[group]]="control","20% off + free shipping","Your last chance to score 20% off + free shipping") -> 20% off + free shipping | H32: 0
F33: control | G33: =IF(ABTest[[#This Row],[group]]="control","20% off + free shipping","Your last chance to score 20% off + free shipping") -> 20% off + free shipping | H33: 0
F34: control | G34: =IF(ABTest[[#This Row],[group]]="control","20% off + free shipping","Your last chance to score 20% off + free shipping") -> 20% off + free shipping | H34: 0
F35: test | G35: =IF(ABTest[[#This Row],[group]]="control","20% off + free shipping","Your last chance to score 20% off + free shipping") -> Your last chance to score 20% off + free shipping | H35: 0
F36: test | G36: =IF(ABTest[[#This Row],[group]]="control","20% off + free shipping","Your last chance to score 20% off + free shipping") -> Your last chance to score 20% off + free shipping | H36: 0
F37: test | G37: =IF(ABTest[[#This Row],[group]]="control","20% off + free shipping","Your last chance to score 20% off + free shipping") -> Your last chance to score 20% off + free shipping | H37: 0
F38: test | G38: =IF(ABTest[[#This Row],[group]]="control","20% off + free shipping","Your last chance to score 20% off + free shipping") -> Your last chance to score 20% off + free shipping | H38: 0
A39: One cofounding factor that could impact the experiment could be delivery time; which impacts when people are available to check their email and see the message. Additionally, is the device they are opening the email on, Whether that be phone or desktop the subject line could be truncated on mobile phones. To mitigate these issues you can make sure the emails are going out at the same time and design the subject line so that the offer is at the front. | F39: control | G39: =IF(ABTest[[#This Row],[group]]="control","20% off + free shipping","Your last chance to score 20% off + free shipping") -> 20% off + free shipping | H39: 0
F40: test | G40: =IF(ABTest[[#This Row],[group]]="control","20% off + free shipping","Your last chance to score 20% off + free shipping") -> Your last chance to score 20% off + free shipping | H40: 1
F41: test | G41: =IF(ABTest[[#This Row],[group]]="control","20% off + free shipping","Your last chance to score 20% off + free shipping") -> Your last chance to score 20% off + free shipping | H41: 0
F42: test | G42: =IF(ABTest[[#This Row],[group]]="control","20% off + free shipping","Your last chance to score 20% off + free shipping") -> Your last chance to score 20% off + free shipping | H42: 1
F43: control | G43: =IF(ABTest[[#This Row],[group]]="control","20% off + free shipping","Your last chance to score 20% off + free shipping") -> 20% off + free shipping | H43: 1
F44: control | G44: =IF(ABTest[[#This Row],[group]]="control","20% off + free shipping","Your last chance to score 20% off + free shipping") -> 20% off + free shipping | H44: 0
F45: test | G45: =IF(ABTest[[#This Row],[group]]="control","20% off + free shipping","Your last chance to score 20% off + free shipping") -> Your last chance to score 20% off + free shipping | H45: 0
F46: control | G46: =IF(ABTest[[#This Row],[group]]="control","20% off + free shipping","Your last chance to score 20% off + free shipping") -> 20% off + free shipping | H46: 0
A47: Part 2: Results Analysis & Interpretation | F47: test | G47: =IF(ABTest[[#This Row],[group]]="control","20% off + free shipping","Your last chance to score 20% off + free shipping") -> Your last chance to score 20% off + free shipping | H47: 0
F48: test | G48: =IF(ABTest[[#This Row],[group]]="control","20% off + free shipping","Your last chance to score 20% off + free shipping") -> Your last chance to score 20% off + free shipping | H48: 0
A49: Data for the A/B Test was collected, and the results can be found in the ABTest data table to the right. In the opened column, 0 indicates that the email was not opened, while 1 indicates the email was opened. | F49: control | G49: =IF(ABTest[[#This Row],[group]]="control","20% off + free shipping","Your last chance to score 20% off + free shipping") -> 20% off + free shipping | H49: 0
F50: control | G50: =IF(ABTest[[#This Row],[group]]="control","20% off + free shipping","Your last chance to score 20% off + free shipping") -> 20% off + free shipping | H50: 0
A51: 6 | B51: In the sheet called PivotTable, create a PivotTable that summarizes the total number of emails sent out to customers in each group, and the number of times each version of the email was opened. It should look like the screenshot! | F51: test | G51: =IF(ABTest[[#This Row],[group]]="control","20% off + free shipping","Your last chance to score 20% off + free shipping") -> Your last chance to score 20% off + free shipping | H51: 0
F52: control | G52: =IF(ABTest[[#This Row],[group]]="control","20% off + free shipping","Your last chance to score 20% off + free shipping") -> 20% off + free shipping | H52: 1
A53: 7 | B53: To check your work, what is the difference in the number of emails sent to each group? | C53: =GETPIVOTDATA("subject line",PivotTable!$B$11,"group","control")-GETPIVOTDATA("subject line",PivotTable!$B$11,"group","test") -> 91 | F53: test | G53: =IF(ABTest[[#This Row],[group]]="control","20% off + free shipping","Your last chance to score 20% off + free shipping") -> Your last chance to score 20% off + free shipping | H53: 0
F54: test | G54: =IF(ABTest[[#This Row],[group]]="control","20% off + free shipping","Your last chance to score 20% off + free shipping") -> Your last chance to score 20% off + free shipping | H54: 0
A55: 8 | B55: What is the difference in the number of emails that were opened in each group? | C55: =GETPIVOTDATA("subject line",PivotTable!$B$11,"group","test","opened",1)-GETPIVOTDATA("subject line",PivotTable!$B$11,"group","control","opened",1) -> 58 | F55: control | G55: =IF(ABTest[[#This Row],[group]]="control","20% off + free shipping","Your last chance to score 20% off + free shipping") -> 20% off + free shipping | H55: 0
F56: control | G56: =IF(ABTest[[#This Row],[group]]="control","20% off + free shipping","Your last chance to score 20% off + free shipping") -> 20% off + free shipping | H56: 1
A57: Use the A/B Test Significance Calculator below to help you answer the following questions. | F57: test | G57: =IF(ABTest[[#This Row],[group]]="control","20% off + free shipping","Your last chance to score 20% off + free shipping") -> Your last chance to score 20% off + free shipping | H57: 1
A58: =HYPERLINK("https://neilpatel.com/ab-testing-calculator/","A/B Testing Significance Calculator") -> A/B Testing Significance Calculator | F58: test | G58: =IF(ABTest[[#This Row],[group]]="control","20% off + free shipping","Your last chance to score 20% off + free shipping") -> Your last chance to score 20% off + free shipping | H58: 0
A59: 9 | B59: Which group performed better, the control or the test group? Are your results statistically significant? | F59: control | G59: =IF(ABTest[[#This Row],[group]]="control","20% off + free shipping","Your last chance to score 20% off + free shipping") -> 20% off + free shipping | H59: 0
F60: test | G60: =IF(ABTest[[#This Row],[group]]="control","20% off + free shipping","Your last chance to score 20% off + free shipping") -> Your last chance to score 20% off + free shipping | H60: 1
A61: Test "B" converted 10% better than Test "A". I am 98% certain that the changes in Test "B" will improve your conversion rate. Your A/B test is statistically significant | F61: control | G61: =IF(ABTest[[#This Row],[group]]="control","20% off + free shipping","Your last chance to score 20% off + free shipping") -> 20% off + free shipping | H61: 0
F62: test | G62: =IF(ABTest[[#This Row],[group]]="control","20% off + free shipping","Your last chance to score 20% off + free shipping") -> Your last chance to score 20% off + free shipping | H62: 0
F63: control | G63: =IF(ABTest[[#This Row],[group]]="control","20% off + free shipping","Your last chance to score 20% off + free shipping") -> 20% off + free shipping | H63: 0
F64: test | G64: =IF(ABTest[[#This Row],[group]]="control","20% off + free shipping","Your last chance to score 20% off + free shipping") -> Your last chance to score 20% off + free shipping | H64: 0
F65: test | G65: =IF(ABTest[[#This Row],[group]]="control","20% off + free shipping","Your last chance to score 20% off + free shipping") -> Your last chance to score 20% off + free shipping | H65: 0
A66: 10 | B66: Since our data is based off of just a sample, it is possible for us to come to an incorrect conclusion. If the truth is in fact different from the conclusion drawn from the data, what type of error would we be making? | F66: control | G66: =IF(ABTest[[#This Row],[group]]="control","20% off + free shipping","Your last chance to score 20% off + free shipping") -> 20% off + free shipping | H66: 0
F67: control | G67: =IF(ABTest[[#This Row],[group]]="control","20% off + free shipping","Your last chance to score 20% off + free shipping") -> 20% off + free shipping | H67: 0
F68: test | G68: =IF(ABTest[[#This Row],[group]]="control","20% off + free shipping","Your last chance to score 20% off + free shipping") -> Your last chance to score 20% off + free shipping | H68: 1
A69: Based off the sample it is possible for us to encounter a sampling error. There potentially could be no real difference in the subject line performing better which would be a false positive. | F69: test | G69: =IF(ABTest[[#This Row],[group]]="control","20% off + free shipping","Your last chance to score 20% off + free shipping") -> Your last chance to score 20% off + free shipping | H69: 0
F70: test | G70: =IF(ABTest[[#This Row],[group]]="control","20% off + free shipping","Your last chance to score 20% off + free shipping") -> Your last chance to score 20% off + free shipping | H70: 0
F71: control | G71: =IF(ABTest[[#This Row],[group]]="control","20% off + free shipping","Your last chance to score 20% off + free shipping") -> 20% off + free shipping | H71: 0
A72: 11 | B72: Based on the results of this test, should H&M continue to send promotional emails with the new subject line? Explain why. Remember you can use ChatGPT as your teammate in helping to interpret these results in the context of your hypothesis and the overall goal of increasing email open rate! | F72: test | G72: =IF(ABTest[[#This Row],[group]]="control","20% off + free shipping","Your last chance to score 20% off + free shipping") -> Your last chance to score 20% off + free shipping | H72: 0
F73: control | G73: =IF(ABTest[[#This Row],[group]]="control","20% off + free shipping","Your last chance to score 20% off + free shipping") -> 20% off + free shipping | H73: 1
F74: control | G74: =IF(ABTest[[#This Row],[group]]="control","20% off + free shipping","Your last chance to score 20% off + free shipping") -> 20% off + free shipping | H74: 0
F75: control | G75: =IF(ABTest[[#This Row],[group]]="control","20% off + free shipping","Your last chance to score 20% off + free shipping") -> 20% off + free shipping | H75: 0
F76: control | G76: =IF(ABTest[[#This Row],[group]]="control","20% off + free shipping","Your last chance to score 20% off + free shipping") -> 20% off + free shipping | H76: 1
A77: H&M should continue to send promotional emails with the new subject line because we are safely within the significance range needed for rejecting the null hypothesis. Although, its not the desired coversion rate, it still makes a big enough impact with litttle to no cost. | F77: test | G77: =IF(ABTest[[#This Row],[group]]="control","20% off + free shipping","Your last chance to score 20% off + free shipping") -> Your last chance to score 20% off + free shipping | H77: 0
F78: control | G78: =IF(ABTest[[#This Row],[group]]="control","20% off + free shipping","Your last chance to score 20% off + free shipping") -> 20% off + free shipping | H78: 0
F79: test | G79: =IF(ABTest[[#This Row],[group]]="control","20% off + free shipping","Your last chance to score 20% off + free shipping") -> Your last chance to score 20% off + free shipping | H79: 1
F80: test | G80: =IF(ABTest[[#This Row],[group]]="control","20% off + free shipping","Your last chance to score 20% off + free shipping") -> Your last chance to score 20% off + free shipping | H80: 0
F81: test | G81: =IF(ABTest[[#This Row],[group]]="control","20% off + free shipping","Your last chance to score 20% off + free shipping") -> Your last chance to score 20% off + free shipping | H81: 0
F82: test | G82: =IF(ABTest[[#This Row],[group]]="control","20% off + free shipping","Your last chance to score 20% off + free shipping") -> Your last chance to score 20% off + free shipping | H82: 1
A83: Part 3: Business Implications | F83: control | G83: =IF(ABTest[[#This Row],[group]]="control","20% off + free shipping","Your last chance to score 20% off + free shipping") -> 20% off + free shipping | H83: 0
F84: control | G84: =IF(ABTest[[#This Row],[group]]="control","20% off + free shipping","Your last chance to score 20% off + free shipping") -> 20% off + free shipping | H84: 0
A85: 12 | B85: If the ‘Your last chance to score 20% off + free shipping’ subject line increases email open rates but potentially leads to lower engagement or fewer purchases (e.g., customers open the email but don’t complete a transaction), how would you balance these factors? What additional data would you need to determine whether the increased open rate translates into meaningful sales? | F85: control | G85: =IF(ABTest[[#This Row],[group]]="control","20% off + free shipping","Your last chance to score 20% off + free shipping") -> 20% off + free shipping | H85: 0
F86: test | G86: =IF(ABTest[[#This Row],[group]]="control","20% off + free shipping","Your last chance to score 20% off + free shipping") -> Your last chance to score 20% off + free shipping | H86: 0
F87: control | G87: =IF(ABTest[[#This Row],[group]]="control","20% off + free shipping","Your last chance to score 20% off + free shipping") -> 20% off + free shipping | H87: 0
F88: control | G88: =IF(ABTest[[#This Row],[group]]="control","20% off + free shipping","Your last chance to score 20% off + free shipping") -> 20% off + free shipping | H88: 0
A89: I would balance these factors by focusing on what will drive the business sales rather than the open rate of an email. I would narrow my A/B testing to how many receipents actually make a purchase when they open the new subject line email. Addtional data to determine open rates translating to meaninful sales would be total revenue generated from each group | F89: test | G89: =IF(ABTest[[#This Row],[group]]="control","20% off + free shipping","Your last chance to score 20% off + free shipping") -> Your last chance to score 20% off + free shipping | H89: 1
F90: control | G90: =IF(ABTest[[#This Row],[group]]="control","20% off + free shipping","Your last chance to score 20% off + free shipping") -> 20% off + free shipping | H90: 0
F91: control | G91: =IF(ABTest[[#This Row],[group]]="control","20% off + free shipping","Your last chance to score 20% off + free shipping") -> 20% off + free shipping | H91: 1
F92: test | G92: =IF(ABTest[[#This Row],[group]]="control","20% off + free shipping","Your last chance to score 20% off + free shipping") -> Your last chance to score 20% off + free shipping | H92: 0
F93: test | G93: =IF(ABTest[[#This Row],[group]]="control","20% off + free shipping","Your last chance to score 20% off + free shipping") -> Your last chance to score 20% off + free shipping | H93: 0
F94: control | G94: =IF(ABTest[[#This Row],[group]]="control","20% off + free shipping","Your last chance to score 20% off + free shipping") -> 20% off + free shipping | H94: 1
F95: control | G95: =IF(ABTest[[#This Row],[group]]="control","20% off + free shipping","Your last chance to score 20% off + free shipping") -> 20% off + free shipping | H95: 0
F96: test | G96: =IF(ABTest[[#This Row],[group]]="control","20% off + free shipping","Your last chance to score 20% off + free shipping") -> Your last chance to score 20% off + free shipping | H96: 0
F97: control | G97: =IF(ABTest[[#This Row],[group]]="control","20% off + free shipping","Your last chance to score 20% off + free shipping") -> 20% off + free shipping | H97: 0
F98: control | G98: =IF(ABTest[[#This Row],[group]]="control","20% off + free shipping","Your last chance to score 20% off + free shipping") -> 20% off + free shipping | H98: 0
F99: test | G99: =IF(ABTest[[#This Row],[group]]="control","20% off + free shipping","Your last chance to score 20% off + free shipping") -> Your last chance to score 20% off + free shipping | H99: 0
F100: control | G100: =IF(ABTest[[#This Row],[group]]="control","20% off + free shipping","Your last chance to score 20% off + free shipping") -> 20% off + free shipping | H100: 1
...

Sheet PivotTable
A9: Your actual PivotTable should go below this line.
B11: Count of subject line | C11: Column Labels
B12: Row Labels | C12: 0 | D12: 1 | E12: Grand Total
B13: control | C13: 3928 | D13: 836 | E13: 4764
B14: test | C14: 3779 | D14: 894 | E14: 4673
B15: Grand Total | C15: 7707 | D15: 1730 | E15: 9437

Sheet Solutions
A1: Question | B1: Low Bound | C1: High Bound | D1: free-response-solution
A2: 1 | B2: free response | D2: =IF(ISBLANK(INDEX('AB Test Analysis'!$A$17:$C$18,1,1)), "no solution", IF(ISERROR(INDEX('AB Test Analysis'!$A$17:$C$18,1,1)), "error in parsing the solution", INDEX('AB Test Analysis'!$A$17:$C$18,1,1))) -> Changing the H&M's subject line from "The appearance of 20% off + free shipping" to "Your last chance to score 20% off + free shipping" will result in no change/Decrease in open rates for the email.
A3: 2 | B3: free response | D3: =IF(ISBLANK(INDEX('AB Test Analysis'!$A$20:$C$21,1,1)), "no solution", IF(ISERROR(INDEX('AB Test Analysis'!$A$20:$C$21,1,1)), "error in parsing the solution", INDEX('AB Test Analysis'!$A$20:$C$21,1,1))) -> Changing the H&M's subject line from "The appearance of 20% off + free shipping" to "Your last chance to score 20% off + free shipping" will result in an increase in open rates for the email.
A4: 3 | B4: 0.11 | C4: 0.1112 | D4: =IF(ISBLANK(INDEX('AB Test Analysis'!$C$26:$C$27,1,1)), "no solution", IF(ISERROR(INDEX('AB Test Analysis'!$C$26:$C$27,1,1)), "error in parsing the solution", INDEX('AB Test Analysis'!$C$26:$C$27,1,1))) -> 0.11
A5: 4 | B5: 9300 | C5: 9400 | D5: =IF(ISBLANK(INDEX('AB Test Analysis'!$C$28:$C$29,1,1)), "no solution", IF(ISERROR(INDEX('AB Test Analysis'!$C$28:$C$29,1,1)), "error in parsing the solution", INDEX('AB Test Analysis'!$C$28:$C$29,1,1))) -> 9300
A6: 5 | B6: free response | D6: =IF(ISBLANK(INDEX('AB Test Analysis'!$A$39:$C$45,1,1)), "no solution", IF(ISERROR(INDEX('AB Test Analysis'!$A$39:$C$45,1,1)), "error in parsing the solution", INDEX('AB Test Analysis'!$A$39:$C$45,1,1))) -> One cofounding factor that could impact the experiment could be delivery time; which impacts when people are available to check their email and see the message. Additionally, is the device they are opening the email on, Whether that be phone or desktop the subject line could be truncated on mobile phones. To mitigate these issues you can make sure the emails are going out at the same time and design the subject line so that the offer is at the front.
A7: 7 | B7: 91 | D7: =IF(ISBLANK(INDEX('AB Test Analysis'!$C$53:$C$54,1,1)), "no solution", IF(ISERROR(INDEX('AB Test Analysis'!$C$53:$C$54,1,1)), "error in parsing the solution", INDEX('AB Test Analysis'!$C$53:$C$54,1,1))) -> 91
A8: 8 | B8: 58 | D8: =IF(ISBLANK(INDEX('AB Test Analysis'!$C$55:$C$56,1,1)), "no solution", IF(ISERROR(INDEX('AB Test Analysis'!$C$55:$C$56,1,1)), "error in parsing the solution", INDEX('AB Test Analysis'!$C$55:$C$56,1,1))) -> 58
A9: 9 | B9: free response | D9: =IF(ISBLANK(INDEX('AB Test Analysis'!$A$61:$C$65,1,1)), "no solution", IF(ISERROR(INDEX('AB Test Analysis'!$A$61:$C$65,1,1)), "error in parsing the solution", INDEX('AB Test Analysis'!$A$61:$C$65,1,1))) -> Test "B" converted 10% better than Test "A". I am 98% certain that the changes in Test "B" will improve your conversion rate. Your A/B test is statistically significant
A10: 10 | B10: free response | D10: =IF(ISBLANK(INDEX('AB Test Analysis'!$A$69:$C$71,1,1)), "no solution", IF(ISERROR(INDEX('AB Test Analysis'!$A$69:$C$71,1,1)), "error in parsing the solution", INDEX('AB Test Analysis'!$A$69:$C$71,1,1))) -> Based off the sample it is possible for us to encounter a sampling error. There potentially could be no real difference in the subject line performing better which would be a false positive.
A11: 11 | B11: free response | D11: =IF(ISBLANK(INDEX('AB Test Analysis'!$A$77:$C$81,1,1)), "no solution", IF(ISERROR(INDEX('AB Test Analysis'!$A$77:$C$81,1,1)), "error in parsing the solution", INDEX('AB Test Analysis'!$A$77:$C$81,1,1))) -> H&M should continue to send promotional emails with the new subject line because we are safely within the significance range needed for rejecting the null hypothesis. Although, its not the desired coversion rate, it still makes a big enough impact with litttle to no cost.
A12: 12 | B12: free response | D12: =IF(ISBLANK(INDEX('AB Test Analysis'!$A$89:$C$95,1,1)), "no solution", IF(ISERROR(INDEX('AB Test Analysis'!$A$89:$C$95,1,1)), "error in parsing the solution", INDEX('AB Test Analysis'!$A$89:$C$95,1,1))) -> I would balance these factors by focusing on what will drive the business sales rather than the open rate of an email. I would narrow my A/B testing to how many receipents actually make a purchase when they open the new subject line email. Addtional data to determine open rates translating to meaninful sales would be total revenue generated from each group
